{
    "_id": 0.39909470584258777,
    "title": "东凤三生情（二十） - 草稿",
    "author": "尊逸",
    "time": "2018.10.13 22:43",
    "words": "字数 1338",
    "views": "阅读 1100",
    "comments": "评论 18",
    "likes": "喜欢 14",
    "content": "第二十二章：\n“东华”凤九绞着东华帝君的一缕白发，似乎有些悲伤\n“嗯？”东华帝君看着凤九，他似乎察觉到了那一丝悲伤，“怎么了？什么事让你不开心了？”\n“没什么……”凤九喃喃道，她想起了那次假装受伤在帝君寝殿里时，帝君说过的话。多么伤情啊！想到这里，眼泪不争气地流了出来\n“九儿，到底怎么了？”东华帝君有些手足无措，她为什么哭呢？\n“东华……”凤九再也憋不住了，搂住东华帝君，狠狠地哭了一顿。好不容易止住了哭，凤九擦擦眼泪，笑着说：“东华，假如有一天，我不在了，你千万不能伤心，我不想看到你伤心，如果实在想我，我在佛铃里做了好多幻像，你想看便看……”凤九事无巨细地交代着，像是诉说着遗言，终于，她说不下去了，将脸埋在帝君的衣袖上，似乎又哭了。良久，她抬起头，冲帝君笑了笑，说：“东华，喝了这杯忘情水，忘了我吧……”\n“九儿，这忘情水，对我无用！九儿，为何说这些？你瞒着我了什么？你要去哪儿？”东华帝君感到慌乱，似乎要失去什么\n“东华……”凤九平静道：“我舍不得你”\n“既然舍不得，那就带上我，你去哪儿，为夫陪你”东华看着凤九，紧了紧臂弯\n“不行，我不能这么自私，带上你，四海八荒怎么办？”凤九笑道\n“没有了你，这四海八荒，不要也罢！”帝君道\n“东华……”凤九抬起头\n“嗯？”东华看向凤九。凤九措不及防给了东华帝君一个吻，这一吻，很长时间。\n“东华，凤九如果真的不在了，千万不要迁怒于他人。更不要太想我，如果你伤心，我也会难过的。”凤九认真地说\n“九儿，别离开我。”东华抱紧了凤九，在她身上，默默加上了天罡罩。\n第二天\n东华一醒来，只见床边多出来一张纸，是凤九留下的，上面写着：\n东华，这是我最后对你说的话了：爱上你，我从未后悔过。假如有来世，假如我能平安无事，凤九定不会离开你。东华，我走了，不要太想我。你知道吗？妖尊渺落醒来了，我也是前天才知道，所以才有了昨天的事。东华，我以前学过上古史，妖尊渺落和浊气只能帝君或帝后以命相抵，才能完全去除。我知道你打算偷偷做了此事，所以，不要怪凤九，比帝君先到一步。帝君，来日再见！\n帝君的手颤抖着，仙遁到了无名山。\n无名山\n帝君赶来时，凤九的最后一丝魂魄刚好散尽。她的仙身徐徐下落，而身后，天兵天将和白家人也都来了。白家人看到此情此景，泣不成声。\n帝君抱着凤九，喃喃道：“你不是说不离开我吗？九儿，你还在怪我吗？九儿，快醒来吧！为夫永远等着你”帝君吻上了那朵凤尾花。不一会儿，凤九的仙身开始泛出柔柔的光辉，只见凤九一丝幻影对东华帝君说：“东华，等我……”便消散了，不一会儿，凤九的仙身也变成尘埃，归于尘土。帝君呆呆的望着这一切，这时，凤九的娘亲晕了过去……\n大家都识趣地散了，独留帝君一个人。\n“九儿，我以为，有我在，你不会有事的。我以为我天地共主东华帝君可以保护你，到头来，你保护了我……九儿，我等你……”东华帝君坐在凤九消失的地方，三天三夜不曾离去。\n狐狸洞里，凤九的亲人们哭得死去活来\n九重天上，白浅哭晕了好几次，成玉哭肿了眼，司命一整天没有说话，连宋一个多月没找帝君下棋，甚至除了照顾成玉，他连门也没有出过。\n帝君也一个多月没去朝会了\n帝君不知道，天君在这一个多月，并没有朝会，整个四海八荒，似乎都为凤九的死默哀。\n东华帝君乃至四海八荒都不知道，凤九还活着，因为有天罡罩护着，她还活着！"
}