{
    "_id": 0.38567309662409566,
    "title": "从古人的避孕方式谈袭人等为何不孕",
    "author": {
        "user_name": "君笺雅侃红楼"
    },
    "time": "2018.09.26 13:01",
    "words": 926,
    "views": 590,
    "comments": 1,
    "likes": 2,
    "content": "古人也会面对避孕的问题，而且古人的避孕也很科学。\n我们还是以《红楼梦》来简单聊聊古人避孕。《红楼梦》虽然没有明确写到古人如何避孕，但我们发现无论是袭人，还是平儿以及所有和男主人发生关系的女孩子都没有怀孕。难道是男主人不行？显然不是。她们以何避孕呢？\n一，计算安全的生理期避孕。\n红楼梦当中，贾家作为兴盛百年的大家族，贾家的规矩是在主人少年时，也就是未婚前在屋里放置几个丫头，名为服侍，其实也是作为主人的性启蒙者。像袭人晴雯等大丫头，其实都是贾宝玉的房中人，贾宝玉是有权利向她们要求性行为。当然这属于自愿的情况，她们也可以拒绝。一，计算安全的生理期避孕。\n但我们看袭人和贾宝玉发生关系后，并没有怀孕，显然贾府对于这一点是会有严格的管理的。每个丫头上岗前一定经过严格培训。如何计算安全生理期，就是由老嬷嬷培训后才可以上岗。袭人显然也不可能天天和贾宝玉在一起。其他几个丫头除了晴雯都和贾宝玉不清不楚。应该都是计算好了自己安全才会和贾宝玉发生关系。不然一旦怀孕，她们也吃不了兜着走。\n二，及时的避孕药。\n少爷们的房中一定有一个宋嬷嬷这样的老年人，也会帮助女孩子们做善后处理。\n贾宝玉算是情感大于肉欲得人。虽然和几个女孩子不清不楚。但并不涉及于乱。贾琏等人就不好说了。我们看贾琏也并没有在和王熙凤婚前有孩子。可知贾家避孕措施完善。宋嬷嬷一类的老人就是主管这些意外情况的。一旦无法确认安全。事后就会有避孕药进行及时阻断。而避孕药在古代已经很成熟。上至皇宫，王公贵族家庭以及民间和妓院都有避孕药的身影，只是相对来说民间往往用得较少。\n三，避孕套。\n说实话中国古人几乎不会用避孕套。避孕套的使用也大多是在欧洲的地区。中国古人不会把他认为不洁的东西用在自己身上。所以类似于像鱼鳔，牲畜膀胱等物，中国古人不会用。《红楼梦》中也完全没有涉及类似的描写。只写到贾琏一沾上多姑娘就不堪的大动，和尤二姐颠鸾倒凤等等。完全不见避孕措施。\n综上，中国古人避孕措施大多是以计算安全生理期，使用避孕药阻断等行为，很少用到避孕套。而像《红楼梦》贾家这样的大家庭，对于怀孕，一定有着极其严格的防范，所以极少出现未婚先孕的情况。\n君笺雅侃红楼，多歧为贵。你的关注将是我写作的最大动力，动动手指，关注一下。没准会开心呢"
}