{
    "_id": 0.40974202835658846,
    "title": "离婚后，前妻和儿子都穿着名牌，知道原因后我后悔当初的决定",
    "author": "逝者君",
    "time": "2018.08.08 20:50",
    "words": "字数 649",
    "views": "阅读 1356",
    "comments": "评论 1",
    "likes": "喜欢 1",
    "content": "导语：离婚后，前妻和儿子都穿着名牌，知道原因后我后悔当初的决定\n文章内容来源于网友真实案例，文中均为化名\n王伟和媳妇离婚了，原因不是你猜的那样，两个人都没有出轨。不过离婚不到三个月，一直勤俭的媳妇尽然穿起了名牌衣服，拿着名牌包包，就连儿子也是一身名牌，知道原因后，王伟后悔自己当初的决定，真是一个傻女人。\n王伟和妻子结婚十年了，前两年关系挺好，后来有了孩子，加上家庭压力太大，两人就总是因为一点小事发生口舌之争，一年，两年，就这样两人吵了八年。都说打是亲骂是爱，可是王伟和妻子都受不了这种生活了，两人决定离婚，从民政局出来的时候，王伟没什么感觉，可从妻子眼里明显能看到一种叫做愉悦的情绪。\n离婚的时候，王伟觉得自己对不起她，再加上快十年了她一直在家带孩子，早和社会脱节了，就把孩子留给了她，房子也转到了她的名下，自己净身出户。可是离婚没多久，王伟就觉得事情不对，前妻朋友圈里晒各种旅游的照片，穿着一身名牌，王伟想着不会这么快就傍上土豪了吧！为了搞清楚原因，就在微信上问她怎么回事，毕竟还有孩子跟着她呢！\n\n这个傻女人，竟然把留给她和孩子的房子卖了，住她妈家，就弟媳那样子的人，住不了多久估计就该撵人了，生活哪像她想的那么简单，真的有点后悔当初把房子过继到她名下，孩子再大点，怎么办？做事不过脑子的女人。\n你们对于王伟媳妇这种做法怎么看？\n有情老师寄语：两个人在一起，时间久了，爱情就变成了亲情，少了激情多了点平淡，别动不动就离婚，离婚你就确定自己下家能找个更好的吗？单身家庭的孩子，真的是种悲哀，躺着挣来的悲哀。"
}